odoo/addons/hr_timesheet_sheet/README.rst
odoo/addons/hr_timesheet_sheet/__init__.py
odoo/addons/hr_timesheet_sheet/__manifest__.py
odoo/addons/hr_timesheet_sheet/data/hr_timesheet_sheet_data.xml
odoo/addons/hr_timesheet_sheet/i18n/af.po
odoo/addons/hr_timesheet_sheet/i18n/am.po
odoo/addons/hr_timesheet_sheet/i18n/ar.po
odoo/addons/hr_timesheet_sheet/i18n/bg.po
odoo/addons/hr_timesheet_sheet/i18n/bs.po
odoo/addons/hr_timesheet_sheet/i18n/ca.po
odoo/addons/hr_timesheet_sheet/i18n/cs.po
odoo/addons/hr_timesheet_sheet/i18n/da.po
odoo/addons/hr_timesheet_sheet/i18n/de.po
odoo/addons/hr_timesheet_sheet/i18n/el.po
odoo/addons/hr_timesheet_sheet/i18n/en_AU.po
odoo/addons/hr_timesheet_sheet/i18n/en_GB.po
odoo/addons/hr_timesheet_sheet/i18n/es.po
odoo/addons/hr_timesheet_sheet/i18n/es_AR.po
odoo/addons/hr_timesheet_sheet/i18n/es_BO.po
odoo/addons/hr_timesheet_sheet/i18n/es_CL.po
odoo/addons/hr_timesheet_sheet/i18n/es_CR.po
odoo/addons/hr_timesheet_sheet/i18n/es_EC.po
odoo/addons/hr_timesheet_sheet/i18n/es_PE.po
odoo/addons/hr_timesheet_sheet/i18n/es_PY.po
odoo/addons/hr_timesheet_sheet/i18n/es_VE.po
odoo/addons/hr_timesheet_sheet/i18n/et.po
odoo/addons/hr_timesheet_sheet/i18n/eu.po
odoo/addons/hr_timesheet_sheet/i18n/fa.po
odoo/addons/hr_timesheet_sheet/i18n/fi.po
odoo/addons/hr_timesheet_sheet/i18n/fo.po
odoo/addons/hr_timesheet_sheet/i18n/fr.po
odoo/addons/hr_timesheet_sheet/i18n/fr_BE.po
odoo/addons/hr_timesheet_sheet/i18n/fr_CA.po
odoo/addons/hr_timesheet_sheet/i18n/fr_FR.po
odoo/addons/hr_timesheet_sheet/i18n/gl.po
odoo/addons/hr_timesheet_sheet/i18n/gu.po
odoo/addons/hr_timesheet_sheet/i18n/he.po
odoo/addons/hr_timesheet_sheet/i18n/hi.po
odoo/addons/hr_timesheet_sheet/i18n/hr.po
odoo/addons/hr_timesheet_sheet/i18n/hr_timesheet_sheet.pot
odoo/addons/hr_timesheet_sheet/i18n/hu.po
odoo/addons/hr_timesheet_sheet/i18n/hy.po
odoo/addons/hr_timesheet_sheet/i18n/id.po
odoo/addons/hr_timesheet_sheet/i18n/is.po
odoo/addons/hr_timesheet_sheet/i18n/it.po
odoo12_addon_hr_timesheet_sheet-12.0.3.7.6.dist-info/METADATA
odoo12_addon_hr_timesheet_sheet-12.0.3.7.6.dist-info/WHEEL
odoo12_addon_hr_timesheet_sheet-12.0.3.7.6.dist-info/top_level.txt
odoo12_addon_hr_timesheet_sheet-12.0.3.7.6.dist-info/RECORD
